streamlit_freegrid/__init__.py
streamlit_freegrid/frontend/build/asset-manifest.json
streamlit_freegrid/frontend/build/bootstrap.min.css
streamlit_freegrid/frontend/build/index.html
streamlit_freegrid/frontend/build/precache-manifest.fd0bde82cfe7d9aecc6edf5cd8710772.js
streamlit_freegrid/frontend/build/service-worker.js
streamlit_freegrid/frontend/build/static/js/2.396cc59b.chunk.js
streamlit_freegrid/frontend/build/static/js/2.396cc59b.chunk.js.LICENSE.txt
streamlit_freegrid/frontend/build/static/js/2.396cc59b.chunk.js.map
streamlit_freegrid/frontend/build/static/js/main.ea466836.chunk.js
streamlit_freegrid/frontend/build/static/js/main.ea466836.chunk.js.map
streamlit_freegrid/frontend/build/static/js/runtime-main.44d30fc2.js
streamlit_freegrid/frontend/build/static/js/runtime-main.44d30fc2.js.map
streamlit_freegrid-0.0.3.dist-info/LICENSE
streamlit_freegrid-0.0.3.dist-info/METADATA
streamlit_freegrid-0.0.3.dist-info/WHEEL
streamlit_freegrid-0.0.3.dist-info/top_level.txt
streamlit_freegrid-0.0.3.dist-info/RECORD
