Metadata-Version: 2.1
Name: streamlit-freegrid
Version: 0.0.3
Summary: Streamlit DataGrid
Home-page: https://github.com/victorC97/streamlit_freegrid
Author: victorC97
Author-email: victor.cour@telecomnancy.net
License: UNKNOWN
Platform: UNKNOWN
Requires-Python: >=3.6
Requires-Dist: streamlit (>=0.63)
